uoishelpers/__init__.py
uoishelpers/_resolvers.py
uoishelpers/authenticationMiddleware.py
uoishelpers/dataloaders.py
uoishelpers/feeders.py
uoishelpers/gqlpermissions.py
uoishelpers/gqlrouter.py
uoishelpers/main.py
uoishelpers/uuid.py
uoishelpers/resolvers/Delete.py
uoishelpers/resolvers/IDType.py
uoishelpers/resolvers/Insert.py
uoishelpers/resolvers/PageResolver.py
uoishelpers/resolvers/ScalarResolver.py
uoishelpers/resolvers/Update.py
uoishelpers/resolvers/VectorResolver.py
uoishelpers/resolvers/__init__.py
uoishelpers/resolvers/fromContext.py
uoishelpers/schema/ProfilingExtension.py
uoishelpers/schema/PrometheusExtension.py
uoishelpers/schema/WhoAmIExtension.py
uoishelpers/schema/__init__.py
uoishelpers-1.4.2.dist-info/licenses/LICENSE
uoishelpers-1.4.2.dist-info/METADATA
uoishelpers-1.4.2.dist-info/WHEEL
uoishelpers-1.4.2.dist-info/top_level.txt
uoishelpers-1.4.2.dist-info/RECORD
